<map>
	<name>
		Classic
	</name>
	<image>
		https://s3.amazonaws.com/ccmaps/Classic.L.jpg
	</image>
	<regions>
		<region>
			<name>
				Anchorage
			</name>
			<bonus>
				1
			</bonus>
		</region>
		<region>
			<name>
				Edmonton
			</name>
			<bonus>
				1
			</bonus>
		</region>
		<region>
			<name>
				Montreal
			</name>
			<bonus>
				1
			</bonus>
		</region>
		<region>
			<name>
				Vancouver
			</name>
			<bonus>
				1
			</bonus>
		</region>
		<region>
			<name>
				Chicago
			</name>
			<bonus>
				1
			</bonus>
		</region>
		<region>
			<name>
				New York
			</name>
			<bonus>
				1
			</bonus>
		</region>
		<region>
			<name>
				Los Angeles
			</name>
			<bonus>
				1
			</bonus>
		</region>
		<region>
			<name>
				Havana
			</name>
			<bonus>
				1
			</bonus>
		</region>
		<region>
			<name>
				Mexico City
			</name>
			<bonus>
				1
			</bonus>
		</region>
		<region>
			<name>
				Bogota
			</name>
			<bonus>
				1
			</bonus>
		</region>
		<region>
			<name>
				Lima
			</name>
			<bonus>
				1
			</bonus>
		</region>
		<region>
			<name>
				Sao Paulo
			</name>
			<bonus>
				1
			</bonus>
		</region>
		<region>
			<name>
				Buenos Aires
			</name>
			<bonus>
				1
			</bonus>
		</region>
		<region>
			<name>
				Dakar
			</name>
			<bonus>
				1
			</bonus>
		</region>
		<region>
			<name>
				Cairo
			</name>
			<bonus>
				1
			</bonus>
		</region>
		<region>
			<name>
				Lagos
			</name>
			<bonus>
				1
			</bonus>
		</region>
		<region>
			<name>
				Nairobi
			</name>
			<bonus>
				1
			</bonus>
		</region>
		<region>
			<name>
				Johannesburg
			</name>
			<bonus>
				1
			</bonus>
		</region>
		<region>
			<name>
				Cape Town
			</name>
			<bonus>
				1
			</bonus>
		</region>
		<region>
			<name>
				Reykjavik
			</name>
			<bonus>
				1
			</bonus>
		</region>
		<region>
			<name>
				Stockholm
			</name>
			<bonus>
				1
			</bonus>
		</region>
		<region>
			<name>
				Moscow
			</name>
			<bonus>
				1
			</bonus>
		</region>
		<region>
			<name>
				London
			</name>
			<bonus>
				1
			</bonus>
		</region>
		<region>
			<name>
				Berlin
			</name>
			<bonus>
				1
			</bonus>
		</region>
		<region>
			<name>
				Madrid
			</name>
			<bonus>
				1
			</bonus>
		</region>
		<region>
			<name>
				Istanbul
			</name>
			<bonus>
				1
			</bonus>
		</region>
		<region>
			<name>
				Astana
			</name>
			<bonus>
				1
			</bonus>
		</region>
		<region>
			<name>
				Novosibirsk
			</name>
			<bonus>
				1
			</bonus>
		</region>
		<region>
			<name>
				Yakutsk
			</name>
			<bonus>
				1
			</bonus>
		</region>
		<region>
			<name>
				Magadan
			</name>
			<bonus>
				1
			</bonus>
		</region>
		<region>
			<name>
				Beijing
			</name>
			<bonus>
				1
			</bonus>
		</region>
		<region>
			<name>
				Tokyo
			</name>
			<bonus>
				1
			</bonus>
		</region>
		<region>
			<name>
				Dubai
			</name>
			<bonus>
				1
			</bonus>
		</region>
		<region>
			<name>
				Delhi
			</name>
			<bonus>
				1
			</bonus>
		</region>
		<region>
			<name>
				Hong Kong
			</name>
			<bonus>
				1
			</bonus>
		</region>
		<region>
			<name>
				Manila
			</name>
			<bonus>
				1
			</bonus>
		</region>
		<region>
			<name>
				Mumbai
			</name>
			<bonus>
				1
			</bonus>
		</region>
		<region>
			<name>
				Bangkok
			</name>
			<bonus>
				1
			</bonus>
		</region>
		<region>
			<name>
				Jakarta
			</name>
			<bonus>
				1
			</bonus>
		</region>
		<region>
			<name>
				Port Moresby
			</name>
			<bonus>
				1
			</bonus>
		</region>
		<region>
			<name>
				Perth
			</name>
			<bonus>
				1
			</bonus>
		</region>
		<region>
			<name>
				Sydney
			</name>
			<bonus>
				1
			</bonus>
		</region>
	</regions>
	<zones>
		<zone>
			<name>
				North America
			</name>
			<bonus>
				15
			</bonus>
			<regions>
				<region>
					<name>
						Anchorage
					</name>
				</region>
				<region>
					<name>
						Edmonton
					</name>
				</region>
				<region>
					<name>
						Montreal
					</name>
				</region>
				<region>
					<name>
						Vancouver
					</name>
				</region>
				<region>
					<name>
						Chicago
					</name>
				</region>
				<region>
					<name>
						New York
					</name>
				</region>
				<region>
					<name>
						Los Angeles
					</name>
				</region>
				<region>
					<name>
						Havana
					</name>
				</region>
				<region>
					<name>
						Mexico City
					</name>
				</region>
			</regions>
		</zone>
		<zone>
			<name>
				South America
			</name>
			<bonus>
				6
			</bonus>
			<regions>
				<region>
					<name>
						Bogota
					</name>
				</region>
				<region>
					<name>
						Lima
					</name>
				</region>
				<region>
					<name>
						Sao Paulo
					</name>
				</region>
				<region>
					<name>
						Buenos Aires
					</name>
				</region>
			</regions>
		</zone>
		<zone>
			<name>
				Africa
			</name>
			<bonus>
				9
			</bonus>
			<regions>
				<region>
					<name>
						Dakar
					</name>
				</region>
				<region>
					<name>
						Cairo
					</name>
				</region>
				<region>
					<name>
						Lagos
					</name>
				</region>
				<region>
					<name>
						Nairobi
					</name>
				</region>
				<region>
					<name>
						Johannesburg
					</name>
				</region>
				<region>
					<name>
						Cape Town
					</name>
				</region>
			</regions>
		</zone>
		<zone>
			<name>
				Europe
			</name>
			<bonus>
				15
			</bonus>
			<regions>
				<region>
					<name>
						Reykjavik
					</name>
				</region>
				<region>
					<name>
						Stockholm
					</name>
				</region>
				<region>
					<name>
						Moscow
					</name>
				</region>
				<region>
					<name>
						London
					</name>
				</region>
				<region>
					<name>
						Berlin
					</name>
				</region>
				<region>
					<name>
						Istanbul
					</name>
				</region>
				<region>
					<name>
						Madrid
					</name>
				</region>
			</regions>
		</zone>
		<zone>
			<name>
				Asia
			</name>
			<bonus>
				21
			</bonus>
			<regions>
				<region>
					<name>
						Astana
					</name>
				</region>
				<region>
					<name>
						Novosibirsk
					</name>
				</region>
				<region>
					<name>
						Yakutsk
					</name>
				</region>
				<region>
					<name>
						Magadan
					</name>
				</region>
				<region>
					<name>
						Beijing
					</name>
				</region>
				<region>
					<name>
						Tokyo
					</name>
				</region>
				<region>
					<name>
						Dubai
					</name>
				</region>
				<region>
					<name>
						Delhi
					</name>
				</region>
				<region>
					<name>
						Hong Kong
					</name>
				</region>
				<region>
					<name>
						Manila
					</name>
				</region>
				<region>
					<name>
						Mumbai
					</name>
				</region>
				<region>
					<name>
						Bangkok
					</name>
				</region>
			</regions>
		</zone>
		<zone>
			<name>
				Oceania
			</name>
			<bonus>
				6
			</bonus>
			<regions>
				<region>
					<name>
						Jakarta
					</name>
				</region>
				<region>
					<name>
						Port Moresby
					</name>
				</region>
				<region>
					<name>
						Perth
					</name>
				</region>
				<region>
					<name>
						Sydney
					</name>
				</region>
			</regions>
		</zone>
	</zones>
	<adjacencies>
		<adjacency>
			<start>
				<region>
					<name>
						Anchorage
					</name>
				</region>
			</start>
			<ends>
				<end>
					<region>
						<name>
							Edmonton
						</name>
					</region>
					<moves>
						<move>
							<name>
								Reinforcement
							</name>
						</move>
						<move>
							<name>
								Assault
							</name>
						</move>
					</moves>
				</end>
				<end>
					<region>
						<name>
							Vancouver
						</name>
					</region>
					<moves>
						<move>
							<name>
								Reinforcement
							</name>
						</move>
						<move>
							<name>
								Assault
							</name>
						</move>
					</moves>
				</end>
				<end>
					<region>
						<name>
							Magadan
						</name>
					</region>
					<moves>
						<move>
							<name>
								Reinforcement
							</name>
						</move>
						<move>
							<name>
								Assault
							</name>
						</move>
					</moves>
				</end>
			</ends>
		</adjacency>
		<adjacency>
			<start>
				<region>
					<name>
						Edmonton
					</name>
				</region>
			</start>
			<ends>
				<end>
					<region>
						<name>
							Anchorage
						</name>
					</region>
					<moves>
						<move>
							<name>
								Reinforcement
							</name>
						</move>
						<move>
							<name>
								Assault
							</name>
						</move>
					</moves>
				</end>
				<end>
					<region>
						<name>
							Vancouver
						</name>
					</region>
					<moves>
						<move>
							<name>
								Reinforcement
							</name>
						</move>
						<move>
							<name>
								Assault
							</name>
						</move>
					</moves>
				</end>
				<end>
					<region>
						<name>
							Chicago
						</name>
					</region>
					<moves>
						<move>
							<name>
								Reinforcement
							</name>
						</move>
						<move>
							<name>
								Assault
							</name>
						</move>
					</moves>
				</end>
				<end>
					<region>
						<name>
							Montreal
						</name>
					</region>
					<moves>
						<move>
							<name>
								Reinforcement
							</name>
						</move>
						<move>
							<name>
								Assault
							</name>
						</move>
					</moves>
				</end>
			</ends>
		</adjacency>
		<adjacency>
			<start>
				<region>
					<name>
						Montreal
					</name>
				</region>
			</start>
			<ends>
				<end>
					<region>
						<name>
							Edmonton
						</name>
					</region>
					<moves>
						<move>
							<name>
								Reinforcement
							</name>
						</move>
						<move>
							<name>
								Assault
							</name>
						</move>
					</moves>
				</end>
				<end>
					<region>
						<name>
							Chicago
						</name>
					</region>
					<moves>
						<move>
							<name>
								Reinforcement
							</name>
						</move>
						<move>
							<name>
								Assault
							</name>
						</move>
					</moves>
				</end>
				<end>
					<region>
						<name>
							New York
						</name>
					</region>
					<moves>
						<move>
							<name>
								Reinforcement
							</name>
						</move>
						<move>
							<name>
								Assault
							</name>
						</move>
					</moves>
				</end>
				<end>
					<region>
						<name>
							Reykjavik
						</name>
					</region>
					<moves>
						<move>
							<name>
								Reinforcement
							</name>
						</move>
						<move>
							<name>
								Assault
							</name>
						</move>
					</moves>
				</end>
			</ends>
		</adjacency>
		<adjacency>
			<start>
				<region>
					<name>
						Vancouver
					</name>
				</region>
			</start>
			<ends>
				<end>
					<region>
						<name>
							Anchorage
						</name>
					</region>
					<moves>
						<move>
							<name>
								Reinforcement
							</name>
						</move>
						<move>
							<name>
								Assault
							</name>
						</move>
					</moves>
				</end>
				<end>
					<region>
						<name>
							Edmonton
						</name>
					</region>
					<moves>
						<move>
							<name>
								Reinforcement
							</name>
						</move>
						<move>
							<name>
								Assault
							</name>
						</move>
					</moves>
				</end>
				<end>
					<region>
						<name>
							Chicago
						</name>
					</region>
					<moves>
						<move>
							<name>
								Reinforcement
							</name>
						</move>
						<move>
							<name>
								Assault
							</name>
						</move>
					</moves>
				</end>
				<end>
					<region>
						<name>
							Los Angeles
						</name>
					</region>
					<moves>
						<move>
							<name>
								Reinforcement
							</name>
						</move>
						<move>
							<name>
								Assault
							</name>
						</move>
					</moves>
				</end>
			</ends>
		</adjacency>
		<adjacency>
			<start>
				<region>
					<name>
						Chicago
					</name>
				</region>
			</start>
			<ends>
				<end>
					<region>
						<name>
							Edmonton
						</name>
					</region>
					<moves>
						<move>
							<name>
								Reinforcement
							</name>
						</move>
						<move>
							<name>
								Assault
							</name>
						</move>
					</moves>
				</end>
				<end>
					<region>
						<name>
							Montreal
						</name>
					</region>
					<moves>
						<move>
							<name>
								Reinforcement
							</name>
						</move>
						<move>
							<name>
								Assault
							</name>
						</move>
					</moves>
				</end>
				<end>
					<region>
						<name>
							Vancouver
						</name>
					</region>
					<moves>
						<move>
							<name>
								Reinforcement
							</name>
						</move>
						<move>
							<name>
								Assault
							</name>
						</move>
					</moves>
				</end>
				<end>
					<region>
						<name>
							New York
						</name>
					</region>
					<moves>
						<move>
							<name>
								Reinforcement
							</name>
						</move>
						<move>
							<name>
								Assault
							</name>
						</move>
					</moves>
				</end>
				<end>
					<region>
						<name>
							Los Angeles
						</name>
					</region>
					<moves>
						<move>
							<name>
								Reinforcement
							</name>
						</move>
						<move>
							<name>
								Assault
							</name>
						</move>
					</moves>
				</end>
				<end>
					<region>
						<name>
							Havana
						</name>
					</region>
					<moves>
						<move>
							<name>
								Reinforcement
							</name>
						</move>
						<move>
							<name>
								Assault
							</name>
						</move>
					</moves>
				</end>
			</ends>
		</adjacency>
		<adjacency>
			<start>
				<region>
					<name>
						New York
					</name>
				</region>
			</start>
			<ends>
				<end>
					<region>
						<name>
							Montreal
						</name>
					</region>
					<moves>
						<move>
							<name>
								Reinforcement
							</name>
						</move>
						<move>
							<name>
								Assault
							</name>
						</move>
					</moves>
				</end>
				<end>
					<region>
						<name>
							Chicago
						</name>
					</region>
					<moves>
						<move>
							<name>
								Reinforcement
							</name>
						</move>
						<move>
							<name>
								Assault
							</name>
						</move>
					</moves>
				</end>
				<end>
					<region>
						<name>
							Havana
						</name>
					</region>
					<moves>
						<move>
							<name>
								Reinforcement
							</name>
						</move>
						<move>
							<name>
								Assault
							</name>
						</move>
					</moves>
				</end>
			</ends>
		</adjacency>
		<adjacency>
			<start>
				<region>
					<name>
						Los Angeles
					</name>
				</region>
			</start>
			<ends>
				<end>
					<region>
						<name>
							Vancouver
						</name>
					</region>
					<moves>
						<move>
							<name>
								Reinforcement
							</name>
						</move>
						<move>
							<name>
								Assault
							</name>
						</move>
					</moves>
				</end>
				<end>
					<region>
						<name>
							Chicago
						</name>
					</region>
					<moves>
						<move>
							<name>
								Reinforcement
							</name>
						</move>
						<move>
							<name>
								Assault
							</name>
						</move>
					</moves>
				</end>
				<end>
					<region>
						<name>
							Havana
						</name>
					</region>
					<moves>
						<move>
							<name>
								Reinforcement
							</name>
						</move>
						<move>
							<name>
								Assault
							</name>
						</move>
					</moves>
				</end>
				<end>
					<region>
						<name>
							Mexico City
						</name>
					</region>
					<moves>
						<move>
							<name>
								Reinforcement
							</name>
						</move>
						<move>
							<name>
								Assault
							</name>
						</move>
					</moves>
				</end>
			</ends>
		</adjacency>
		<adjacency>
			<start>
				<region>
					<name>
						Havana
					</name>
				</region>
			</start>
			<ends>
				<end>
					<region>
						<name>
							Chicago
						</name>
					</region>
					<moves>
						<move>
							<name>
								Reinforcement
							</name>
						</move>
						<move>
							<name>
								Assault
							</name>
						</move>
					</moves>
				</end>
				<end>
					<region>
						<name>
							New York
						</name>
					</region>
					<moves>
						<move>
							<name>
								Reinforcement
							</name>
						</move>
						<move>
							<name>
								Assault
							</name>
						</move>
					</moves>
				</end>
				<end>
					<region>
						<name>
							Los Angeles
						</name>
					</region>
					<moves>
						<move>
							<name>
								Reinforcement
							</name>
						</move>
						<move>
							<name>
								Assault
							</name>
						</move>
					</moves>
				</end>
				<end>
					<region>
						<name>
							Mexico City
						</name>
					</region>
					<moves>
						<move>
							<name>
								Reinforcement
							</name>
						</move>
						<move>
							<name>
								Assault
							</name>
						</move>
					</moves>
				</end>
			</ends>
		</adjacency>
		<adjacency>
			<start>
				<region>
					<name>
						Mexico City
					</name>
				</region>
			</start>
			<ends>
				<end>
					<region>
						<name>
							Los Angeles
						</name>
					</region>
					<moves>
						<move>
							<name>
								Reinforcement
							</name>
						</move>
						<move>
							<name>
								Assault
							</name>
						</move>
					</moves>
				</end>
				<end>
					<region>
						<name>
							Havana
						</name>
					</region>
					<moves>
						<move>
							<name>
								Reinforcement
							</name>
						</move>
						<move>
							<name>
								Assault
							</name>
						</move>
					</moves>
				</end>
				<end>
					<region>
						<name>
							Bogota
						</name>
					</region>
					<moves>
						<move>
							<name>
								Reinforcement
							</name>
						</move>
						<move>
							<name>
								Assault
							</name>
						</move>
					</moves>
				</end>
			</ends>
		</adjacency>
		<adjacency>
			<start>
				<region>
					<name>
						Bogota
					</name>
				</region>
			</start>
			<ends>
				<end>
					<region>
						<name>
							Mexico City
						</name>
					</region>
					<moves>
						<move>
							<name>
								Reinforcement
							</name>
						</move>
						<move>
							<name>
								Assault
							</name>
						</move>
					</moves>
				</end>
				<end>
					<region>
						<name>
							Lima
						</name>
					</region>
					<moves>
						<move>
							<name>
								Reinforcement
							</name>
						</move>
						<move>
							<name>
								Assault
							</name>
						</move>
					</moves>
				</end>
				<end>
					<region>
						<name>
							Sao Paulo
						</name>
					</region>
					<moves>
						<move>
							<name>
								Reinforcement
							</name>
						</move>
						<move>
							<name>
								Assault
							</name>
						</move>
					</moves>
				</end>
			</ends>
		</adjacency>
		<adjacency>
			<start>
				<region>
					<name>
						Lima
					</name>
				</region>
			</start>
			<ends>
				<end>
					<region>
						<name>
							Bogota
						</name>
					</region>
					<moves>
						<move>
							<name>
								Reinforcement
							</name>
						</move>
						<move>
							<name>
								Assault
							</name>
						</move>
					</moves>
				</end>
				<end>
					<region>
						<name>
							Sao Paulo
						</name>
					</region>
					<moves>
						<move>
							<name>
								Reinforcement
							</name>
						</move>
						<move>
							<name>
								Assault
							</name>
						</move>
					</moves>
				</end>
				<end>
					<region>
						<name>
							Buenos Aires
						</name>
					</region>
					<moves>
						<move>
							<name>
								Reinforcement
							</name>
						</move>
						<move>
							<name>
								Assault
							</name>
						</move>
					</moves>
				</end>
			</ends>
		</adjacency>
		<adjacency>
			<start>
				<region>
					<name>
						Sao Paulo
					</name>
				</region>
			</start>
			<ends>
				<end>
					<region>
						<name>
							Bogota
						</name>
					</region>
					<moves>
						<move>
							<name>
								Reinforcement
							</name>
						</move>
						<move>
							<name>
								Assault
							</name>
						</move>
					</moves>
				</end>
				<end>
					<region>
						<name>
							Lima
						</name>
					</region>
					<moves>
						<move>
							<name>
								Reinforcement
							</name>
						</move>
						<move>
							<name>
								Assault
							</name>
						</move>
					</moves>
				</end>
				<end>
					<region>
						<name>
							Buenos Aires
						</name>
					</region>
					<moves>
						<move>
							<name>
								Reinforcement
							</name>
						</move>
						<move>
							<name>
								Assault
							</name>
						</move>
					</moves>
				</end>
				<end>
					<region>
						<name>
							Dakar
						</name>
					</region>
					<moves>
						<move>
							<name>
								Reinforcement
							</name>
						</move>
						<move>
							<name>
								Assault
							</name>
						</move>
					</moves>
				</end>
			</ends>
		</adjacency>
		<adjacency>
			<start>
				<region>
					<name>
						Buenos Aires
					</name>
				</region>
			</start>
			<ends>
				<end>
					<region>
						<name>
							Lima
						</name>
					</region>
					<moves>
						<move>
							<name>
								Reinforcement
							</name>
						</move>
						<move>
							<name>
								Assault
							</name>
						</move>
					</moves>
				</end>
				<end>
					<region>
						<name>
							Sao Paulo
						</name>
					</region>
					<moves>
						<move>
							<name>
								Reinforcement
							</name>
						</move>
						<move>
							<name>
								Assault
							</name>
						</move>
					</moves>
				</end>
			</ends>
		</adjacency>
		<adjacency>
			<start>
				<region>
					<name>
						Dakar
					</name>
				</region>
			</start>
			<ends>
				<end>
					<region>
						<name>
							Sao Paulo
						</name>
					</region>
					<moves>
						<move>
							<name>
								Reinforcement
							</name>
						</move>
						<move>
							<name>
								Assault
							</name>
						</move>
					</moves>
				</end>
				<end>
					<region>
						<name>
							Cairo
						</name>
					</region>
					<moves>
						<move>
							<name>
								Reinforcement
							</name>
						</move>
						<move>
							<name>
								Assault
							</name>
						</move>
					</moves>
				</end>
				<end>
					<region>
						<name>
							Lagos
						</name>
					</region>
					<moves>
						<move>
							<name>
								Reinforcement
							</name>
						</move>
						<move>
							<name>
								Assault
							</name>
						</move>
					</moves>
				</end>
				<end>
					<region>
						<name>
							Nairobi
						</name>
					</region>
					<moves>
						<move>
							<name>
								Reinforcement
							</name>
						</move>
						<move>
							<name>
								Assault
							</name>
						</move>
					</moves>
				</end>
				<end>
					<region>
						<name>
							Madrid
						</name>
					</region>
					<moves>
						<move>
							<name>
								Reinforcement
							</name>
						</move>
						<move>
							<name>
								Assault
							</name>
						</move>
					</moves>
				</end>
				<end>
					<region>
						<name>
							Istanbul
						</name>
					</region>
					<moves>
						<move>
							<name>
								Reinforcement
							</name>
						</move>
						<move>
							<name>
								Assault
							</name>
						</move>
					</moves>
				</end>
			</ends>
		</adjacency>
		<adjacency>
			<start>
				<region>
					<name>
						Cairo
					</name>
				</region>
			</start>
			<ends>
				<end>
					<region>
						<name>
							Dakar
						</name>
					</region>
					<moves>
						<move>
							<name>
								Reinforcement
							</name>
						</move>
						<move>
							<name>
								Assault
							</name>
						</move>
					</moves>
				</end>
				<end>
					<region>
						<name>
							Nairobi
						</name>
					</region>
					<moves>
						<move>
							<name>
								Reinforcement
							</name>
						</move>
						<move>
							<name>
								Assault
							</name>
						</move>
					</moves>
				</end>
				<end>
					<region>
						<name>
							Istanbul
						</name>
					</region>
					<moves>
						<move>
							<name>
								Reinforcement
							</name>
						</move>
						<move>
							<name>
								Assault
							</name>
						</move>
					</moves>
				</end>
				<end>
					<region>
						<name>
							Dubai
						</name>
					</region>
					<moves>
						<move>
							<name>
								Reinforcement
							</name>
						</move>
						<move>
							<name>
								Assault
							</name>
						</move>
					</moves>
				</end>
			</ends>
		</adjacency>
		<adjacency>
			<start>
				<region>
					<name>
						Lagos
					</name>
				</region>
			</start>
			<ends>
				<end>
					<region>
						<name>
							Dakar
						</name>
					</region>
					<moves>
						<move>
							<name>
								Reinforcement
							</name>
						</move>
						<move>
							<name>
								Assault
							</name>
						</move>
					</moves>
				</end>
				<end>
					<region>
						<name>
							Nairobi
						</name>
					</region>
					<moves>
						<move>
							<name>
								Reinforcement
							</name>
						</move>
						<move>
							<name>
								Assault
							</name>
						</move>
					</moves>
				</end>
				<end>
					<region>
						<name>
							Cape Town
						</name>
					</region>
					<moves>
						<move>
							<name>
								Reinforcement
							</name>
						</move>
						<move>
							<name>
								Assault
							</name>
						</move>
					</moves>
				</end>
			</ends>
		</adjacency>
		<adjacency>
			<start>
				<region>
					<name>
						Nairobi
					</name>
				</region>
			</start>
			<ends>
				<end>
					<region>
						<name>
							Dakar
						</name>
					</region>
					<moves>
						<move>
							<name>
								Reinforcement
							</name>
						</move>
						<move>
							<name>
								Assault
							</name>
						</move>
					</moves>
				</end>
				<end>
					<region>
						<name>
							Cairo
						</name>
					</region>
					<moves>
						<move>
							<name>
								Reinforcement
							</name>
						</move>
						<move>
							<name>
								Assault
							</name>
						</move>
					</moves>
				</end>
				<end>
					<region>
						<name>
							Lagos
						</name>
					</region>
					<moves>
						<move>
							<name>
								Reinforcement
							</name>
						</move>
						<move>
							<name>
								Assault
							</name>
						</move>
					</moves>
				</end>
				<end>
					<region>
						<name>
							Cape Town
						</name>
					</region>
					<moves>
						<move>
							<name>
								Reinforcement
							</name>
						</move>
						<move>
							<name>
								Assault
							</name>
						</move>
					</moves>
				</end>
				<end>
					<region>
						<name>
							Johannesburg
						</name>
					</region>
					<moves>
						<move>
							<name>
								Reinforcement
							</name>
						</move>
						<move>
							<name>
								Assault
							</name>
						</move>
					</moves>
				</end>
				<end>
					<region>
						<name>
							Dubai
						</name>
					</region>
					<moves>
						<move>
							<name>
								Reinforcement
							</name>
						</move>
						<move>
							<name>
								Assault
							</name>
						</move>
					</moves>
				</end>
			</ends>
		</adjacency>
		<adjacency>
			<start>
				<region>
					<name>
						Cape Town
					</name>
				</region>
			</start>
			<ends>
				<end>
					<region>
						<name>
							Lagos
						</name>
					</region>
					<moves>
						<move>
							<name>
								Reinforcement
							</name>
						</move>
						<move>
							<name>
								Assault
							</name>
						</move>
					</moves>
				</end>
				<end>
					<region>
						<name>
							Nairobi
						</name>
					</region>
					<moves>
						<move>
							<name>
								Reinforcement
							</name>
						</move>
						<move>
							<name>
								Assault
							</name>
						</move>
					</moves>
				</end>
				<end>
					<region>
						<name>
							Johannesburg
						</name>
					</region>
					<moves>
						<move>
							<name>
								Reinforcement
							</name>
						</move>
						<move>
							<name>
								Assault
							</name>
						</move>
					</moves>
				</end>
			</ends>
		</adjacency>
		<adjacency>
			<start>
				<region>
					<name>
						Johannesburg
					</name>
				</region>
			</start>
			<ends>
				<end>
					<region>
						<name>
							Nairobi
						</name>
					</region>
					<moves>
						<move>
							<name>
								Reinforcement
							</name>
						</move>
						<move>
							<name>
								Assault
							</name>
						</move>
					</moves>
				</end>
				<end>
					<region>
						<name>
							Cape Town
						</name>
					</region>
					<moves>
						<move>
							<name>
								Reinforcement
							</name>
						</move>
						<move>
							<name>
								Assault
							</name>
						</move>
					</moves>
				</end>
			</ends>
		</adjacency>
		<adjacency>
			<start>
				<region>
					<name>
						Reykjavik
					</name>
				</region>
			</start>
			<ends>
				<end>
					<region>
						<name>
							Montreal
						</name>
					</region>
					<moves>
						<move>
							<name>
								Reinforcement
							</name>
						</move>
						<move>
							<name>
								Assault
							</name>
						</move>
					</moves>
				</end>
				<end>
					<region>
						<name>
							Stockholm
						</name>
					</region>
					<moves>
						<move>
							<name>
								Reinforcement
							</name>
						</move>
						<move>
							<name>
								Assault
							</name>
						</move>
					</moves>
				</end>
				<end>
					<region>
						<name>
							London
						</name>
					</region>
					<moves>
						<move>
							<name>
								Reinforcement
							</name>
						</move>
						<move>
							<name>
								Assault
							</name>
						</move>
					</moves>
				</end>
			</ends>
		</adjacency>
		<adjacency>
			<start>
				<region>
					<name>
						Stockholm
					</name>
				</region>
			</start>
			<ends>
				<end>
					<region>
						<name>
							Reykjavik
						</name>
					</region>
					<moves>
						<move>
							<name>
								Reinforcement
							</name>
						</move>
						<move>
							<name>
								Assault
							</name>
						</move>
					</moves>
				</end>
				<end>
					<region>
						<name>
							London
						</name>
					</region>
					<moves>
						<move>
							<name>
								Reinforcement
							</name>
						</move>
						<move>
							<name>
								Assault
							</name>
						</move>
					</moves>
				</end>
				<end>
					<region>
						<name>
							Berlin
						</name>
					</region>
					<moves>
						<move>
							<name>
								Reinforcement
							</name>
						</move>
						<move>
							<name>
								Assault
							</name>
						</move>
					</moves>
				</end>
				<end>
					<region>
						<name>
							Moscow
						</name>
					</region>
					<moves>
						<move>
							<name>
								Reinforcement
							</name>
						</move>
						<move>
							<name>
								Assault
							</name>
						</move>
					</moves>
				</end>
			</ends>
		</adjacency>
		<adjacency>
			<start>
				<region>
					<name>
						Moscow
					</name>
				</region>
			</start>
			<ends>
				<end>
					<region>
						<name>
							Stockholm
						</name>
					</region>
					<moves>
						<move>
							<name>
								Reinforcement
							</name>
						</move>
						<move>
							<name>
								Assault
							</name>
						</move>
					</moves>
				</end>
				<end>
					<region>
						<name>
							Berlin
						</name>
					</region>
					<moves>
						<move>
							<name>
								Reinforcement
							</name>
						</move>
						<move>
							<name>
								Assault
							</name>
						</move>
					</moves>
				</end>
				<end>
					<region>
						<name>
							Istanbul
						</name>
					</region>
					<moves>
						<move>
							<name>
								Reinforcement
							</name>
						</move>
						<move>
							<name>
								Assault
							</name>
						</move>
					</moves>
				</end>
				<end>
					<region>
						<name>
							Astana
						</name>
					</region>
					<moves>
						<move>
							<name>
								Reinforcement
							</name>
						</move>
						<move>
							<name>
								Assault
							</name>
						</move>
					</moves>
				</end>
				<end>
					<region>
						<name>
							Dubai
						</name>
					</region>
					<moves>
						<move>
							<name>
								Reinforcement
							</name>
						</move>
						<move>
							<name>
								Assault
							</name>
						</move>
					</moves>
				</end>
				<end>
					<region>
						<name>
							Delhi
						</name>
					</region>
					<moves>
						<move>
							<name>
								Reinforcement
							</name>
						</move>
						<move>
							<name>
								Assault
							</name>
						</move>
					</moves>
				</end>
			</ends>
		</adjacency>
		<adjacency>
			<start>
				<region>
					<name>
						London
					</name>
				</region>
			</start>
			<ends>
				<end>
					<region>
						<name>
							Reykjavik
						</name>
					</region>
					<moves>
						<move>
							<name>
								Reinforcement
							</name>
						</move>
						<move>
							<name>
								Assault
							</name>
						</move>
					</moves>
				</end>
				<end>
					<region>
						<name>
							Stockholm
						</name>
					</region>
					<moves>
						<move>
							<name>
								Reinforcement
							</name>
						</move>
						<move>
							<name>
								Assault
							</name>
						</move>
					</moves>
				</end>
				<end>
					<region>
						<name>
							Berlin
						</name>
					</region>
					<moves>
						<move>
							<name>
								Reinforcement
							</name>
						</move>
						<move>
							<name>
								Assault
							</name>
						</move>
					</moves>
				</end>
				<end>
					<region>
						<name>
							Madrid
						</name>
					</region>
					<moves>
						<move>
							<name>
								Reinforcement
							</name>
						</move>
						<move>
							<name>
								Assault
							</name>
						</move>
					</moves>
				</end>
			</ends>
		</adjacency>
		<adjacency>
			<start>
				<region>
					<name>
						Berlin
					</name>
				</region>
			</start>
			<ends>
				<end>
					<region>
						<name>
							Stockholm
						</name>
					</region>
					<moves>
						<move>
							<name>
								Reinforcement
							</name>
						</move>
						<move>
							<name>
								Assault
							</name>
						</move>
					</moves>
				</end>
				<end>
					<region>
						<name>
							Moscow
						</name>
					</region>
					<moves>
						<move>
							<name>
								Reinforcement
							</name>
						</move>
						<move>
							<name>
								Assault
							</name>
						</move>
					</moves>
				</end>
				<end>
					<region>
						<name>
							London
						</name>
					</region>
					<moves>
						<move>
							<name>
								Reinforcement
							</name>
						</move>
						<move>
							<name>
								Assault
							</name>
						</move>
					</moves>
				</end>
				<end>
					<region>
						<name>
							Madrid
						</name>
					</region>
					<moves>
						<move>
							<name>
								Reinforcement
							</name>
						</move>
						<move>
							<name>
								Assault
							</name>
						</move>
					</moves>
				</end>
				<end>
					<region>
						<name>
							Istanbul
						</name>
					</region>
					<moves>
						<move>
							<name>
								Reinforcement
							</name>
						</move>
						<move>
							<name>
								Assault
							</name>
						</move>
					</moves>
				</end>
			</ends>
		</adjacency>
		<adjacency>
			<start>
				<region>
					<name>
						Madrid
					</name>
				</region>
			</start>
			<ends>
				<end>
					<region>
						<name>
							Dakar
						</name>
					</region>
					<moves>
						<move>
							<name>
								Reinforcement
							</name>
						</move>
						<move>
							<name>
								Assault
							</name>
						</move>
					</moves>
				</end>
				<end>
					<region>
						<name>
							London
						</name>
					</region>
					<moves>
						<move>
							<name>
								Reinforcement
							</name>
						</move>
						<move>
							<name>
								Assault
							</name>
						</move>
					</moves>
				</end>
				<end>
					<region>
						<name>
							Berlin
						</name>
					</region>
					<moves>
						<move>
							<name>
								Reinforcement
							</name>
						</move>
						<move>
							<name>
								Assault
							</name>
						</move>
					</moves>
				</end>
				<end>
					<region>
						<name>
							Istanbul
						</name>
					</region>
					<moves>
						<move>
							<name>
								Reinforcement
							</name>
						</move>
						<move>
							<name>
								Assault
							</name>
						</move>
					</moves>
				</end>
			</ends>
		</adjacency>
		<adjacency>
			<start>
				<region>
					<name>
						Istanbul
					</name>
				</region>
			</start>
			<ends>
				<end>
					<region>
						<name>
							Dakar
						</name>
					</region>
					<moves>
						<move>
							<name>
								Reinforcement
							</name>
						</move>
						<move>
							<name>
								Assault
							</name>
						</move>
					</moves>
				</end>
				<end>
					<region>
						<name>
							Cairo
						</name>
					</region>
					<moves>
						<move>
							<name>
								Reinforcement
							</name>
						</move>
						<move>
							<name>
								Assault
							</name>
						</move>
					</moves>
				</end>
				<end>
					<region>
						<name>
							Moscow
						</name>
					</region>
					<moves>
						<move>
							<name>
								Reinforcement
							</name>
						</move>
						<move>
							<name>
								Assault
							</name>
						</move>
					</moves>
				</end>
				<end>
					<region>
						<name>
							Berlin
						</name>
					</region>
					<moves>
						<move>
							<name>
								Reinforcement
							</name>
						</move>
						<move>
							<name>
								Assault
							</name>
						</move>
					</moves>
				</end>
				<end>
					<region>
						<name>
							Madrid
						</name>
					</region>
					<moves>
						<move>
							<name>
								Reinforcement
							</name>
						</move>
						<move>
							<name>
								Assault
							</name>
						</move>
					</moves>
				</end>
				<end>
					<region>
						<name>
							Dubai
						</name>
					</region>
					<moves>
						<move>
							<name>
								Reinforcement
							</name>
						</move>
						<move>
							<name>
								Assault
							</name>
						</move>
					</moves>
				</end>
			</ends>
		</adjacency>
		<adjacency>
			<start>
				<region>
					<name>
						Astana
					</name>
				</region>
			</start>
			<ends>
				<end>
					<region>
						<name>
							Moscow
						</name>
					</region>
					<moves>
						<move>
							<name>
								Reinforcement
							</name>
						</move>
						<move>
							<name>
								Assault
							</name>
						</move>
					</moves>
				</end>
				<end>
					<region>
						<name>
							Novosibirsk
						</name>
					</region>
					<moves>
						<move>
							<name>
								Reinforcement
							</name>
						</move>
						<move>
							<name>
								Assault
							</name>
						</move>
					</moves>
				</end>
				<end>
					<region>
						<name>
							Delhi
						</name>
					</region>
					<moves>
						<move>
							<name>
								Reinforcement
							</name>
						</move>
						<move>
							<name>
								Assault
							</name>
						</move>
					</moves>
				</end>
				<end>
					<region>
						<name>
							Hong Kong
						</name>
					</region>
					<moves>
						<move>
							<name>
								Reinforcement
							</name>
						</move>
						<move>
							<name>
								Assault
							</name>
						</move>
					</moves>
				</end>
			</ends>
		</adjacency>
		<adjacency>
			<start>
				<region>
					<name>
						Novosibirsk
					</name>
				</region>
			</start>
			<ends>
				<end>
					<region>
						<name>
							Astana
						</name>
					</region>
					<moves>
						<move>
							<name>
								Reinforcement
							</name>
						</move>
						<move>
							<name>
								Assault
							</name>
						</move>
					</moves>
				</end>
				<end>
					<region>
						<name>
							Yakutsk
						</name>
					</region>
					<moves>
						<move>
							<name>
								Reinforcement
							</name>
						</move>
						<move>
							<name>
								Assault
							</name>
						</move>
					</moves>
				</end>
				<end>
					<region>
						<name>
							Beijing
						</name>
					</region>
					<moves>
						<move>
							<name>
								Reinforcement
							</name>
						</move>
						<move>
							<name>
								Assault
							</name>
						</move>
					</moves>
				</end>
				<end>
					<region>
						<name>
							Hong Kong
						</name>
					</region>
					<moves>
						<move>
							<name>
								Reinforcement
							</name>
						</move>
						<move>
							<name>
								Assault
							</name>
						</move>
					</moves>
				</end>
				<end>
					<region>
						<name>
							Manila
						</name>
					</region>
					<moves>
						<move>
							<name>
								Reinforcement
							</name>
						</move>
						<move>
							<name>
								Assault
							</name>
						</move>
					</moves>
				</end>
			</ends>
		</adjacency>
		<adjacency>
			<start>
				<region>
					<name>
						Yakutsk
					</name>
				</region>
			</start>
			<ends>
				<end>
					<region>
						<name>
							Novosibirsk
						</name>
					</region>
					<moves>
						<move>
							<name>
								Reinforcement
							</name>
						</move>
						<move>
							<name>
								Assault
							</name>
						</move>
					</moves>
				</end>
				<end>
					<region>
						<name>
							Magadan
						</name>
					</region>
					<moves>
						<move>
							<name>
								Reinforcement
							</name>
						</move>
						<move>
							<name>
								Assault
							</name>
						</move>
					</moves>
				</end>
				<end>
					<region>
						<name>
							Beijing
						</name>
					</region>
					<moves>
						<move>
							<name>
								Reinforcement
							</name>
						</move>
						<move>
							<name>
								Assault
							</name>
						</move>
					</moves>
				</end>
			</ends>
		</adjacency>
		<adjacency>
			<start>
				<region>
					<name>
						Magadan
					</name>
				</region>
			</start>
			<ends>
				<end>
					<region>
						<name>
							Anchorage
						</name>
					</region>
					<moves>
						<move>
							<name>
								Reinforcement
							</name>
						</move>
						<move>
							<name>
								Assault
							</name>
						</move>
					</moves>
				</end>
				<end>
					<region>
						<name>
							Yakutsk
						</name>
					</region>
					<moves>
						<move>
							<name>
								Reinforcement
							</name>
						</move>
						<move>
							<name>
								Assault
							</name>
						</move>
					</moves>
				</end>
				<end>
					<region>
						<name>
							Beijing
						</name>
					</region>
					<moves>
						<move>
							<name>
								Reinforcement
							</name>
						</move>
						<move>
							<name>
								Assault
							</name>
						</move>
					</moves>
				</end>
				<end>
					<region>
						<name>
							Tokyo
						</name>
					</region>
					<moves>
						<move>
							<name>
								Reinforcement
							</name>
						</move>
						<move>
							<name>
								Assault
							</name>
						</move>
					</moves>
				</end>
			</ends>
		</adjacency>
		<adjacency>
			<start>
				<region>
					<name>
						Beijing
					</name>
				</region>
			</start>
			<ends>
				<end>
					<region>
						<name>
							Novosibirsk
						</name>
					</region>
					<moves>
						<move>
							<name>
								Reinforcement
							</name>
						</move>
						<move>
							<name>
								Assault
							</name>
						</move>
					</moves>
				</end>
				<end>
					<region>
						<name>
							Yakutsk
						</name>
					</region>
					<moves>
						<move>
							<name>
								Reinforcement
							</name>
						</move>
						<move>
							<name>
								Assault
							</name>
						</move>
					</moves>
				</end>
				<end>
					<region>
						<name>
							Magadan
						</name>
					</region>
					<moves>
						<move>
							<name>
								Reinforcement
							</name>
						</move>
						<move>
							<name>
								Assault
							</name>
						</move>
					</moves>
				</end>
				<end>
					<region>
						<name>
							Manila
						</name>
					</region>
					<moves>
						<move>
							<name>
								Reinforcement
							</name>
						</move>
						<move>
							<name>
								Assault
							</name>
						</move>
					</moves>
				</end>
			</ends>
		</adjacency>
		<adjacency>
			<start>
				<region>
					<name>
						Tokyo
					</name>
				</region>
			</start>
			<ends>
				<end>
					<region>
						<name>
							Magadan
						</name>
					</region>
					<moves>
						<move>
							<name>
								Reinforcement
							</name>
						</move>
						<move>
							<name>
								Assault
							</name>
						</move>
					</moves>
				</end>
				<end>
					<region>
						<name>
							Manila
						</name>
					</region>
					<moves>
						<move>
							<name>
								Reinforcement
							</name>
						</move>
						<move>
							<name>
								Assault
							</name>
						</move>
					</moves>
				</end>
			</ends>
		</adjacency>
		<adjacency>
			<start>
				<region>
					<name>
						Dubai
					</name>
				</region>
			</start>
			<ends>
				<end>
					<region>
						<name>
							Cairo
						</name>
					</region>
					<moves>
						<move>
							<name>
								Reinforcement
							</name>
						</move>
						<move>
							<name>
								Assault
							</name>
						</move>
					</moves>
				</end>
				<end>
					<region>
						<name>
							Nairobi
						</name>
					</region>
					<moves>
						<move>
							<name>
								Reinforcement
							</name>
						</move>
						<move>
							<name>
								Assault
							</name>
						</move>
					</moves>
				</end>
				<end>
					<region>
						<name>
							Moscow
						</name>
					</region>
					<moves>
						<move>
							<name>
								Reinforcement
							</name>
						</move>
						<move>
							<name>
								Assault
							</name>
						</move>
					</moves>
				</end>
				<end>
					<region>
						<name>
							Istanbul
						</name>
					</region>
					<moves>
						<move>
							<name>
								Reinforcement
							</name>
						</move>
						<move>
							<name>
								Assault
							</name>
						</move>
					</moves>
				</end>
				<end>
					<region>
						<name>
							Delhi
						</name>
					</region>
					<moves>
						<move>
							<name>
								Reinforcement
							</name>
						</move>
						<move>
							<name>
								Assault
							</name>
						</move>
					</moves>
				</end>
				<end>
					<region>
						<name>
							Mumbai
						</name>
					</region>
					<moves>
						<move>
							<name>
								Reinforcement
							</name>
						</move>
						<move>
							<name>
								Assault
							</name>
						</move>
					</moves>
				</end>
			</ends>
		</adjacency>
		<adjacency>
			<start>
				<region>
					<name>
						Delhi
					</name>
				</region>
			</start>
			<ends>
				<end>
					<region>
						<name>
							Moscow
						</name>
					</region>
					<moves>
						<move>
							<name>
								Reinforcement
							</name>
						</move>
						<move>
							<name>
								Assault
							</name>
						</move>
					</moves>
				</end>
				<end>
					<region>
						<name>
							Astana
						</name>
					</region>
					<moves>
						<move>
							<name>
								Reinforcement
							</name>
						</move>
						<move>
							<name>
								Assault
							</name>
						</move>
					</moves>
				</end>
				<end>
					<region>
						<name>
							Dubai
						</name>
					</region>
					<moves>
						<move>
							<name>
								Reinforcement
							</name>
						</move>
						<move>
							<name>
								Assault
							</name>
						</move>
					</moves>
				</end>
				<end>
					<region>
						<name>
							Hong Kong
						</name>
					</region>
					<moves>
						<move>
							<name>
								Reinforcement
							</name>
						</move>
						<move>
							<name>
								Assault
							</name>
						</move>
					</moves>
				</end>
				<end>
					<region>
						<name>
							Mumbai
						</name>
					</region>
					<moves>
						<move>
							<name>
								Reinforcement
							</name>
						</move>
						<move>
							<name>
								Assault
							</name>
						</move>
					</moves>
				</end>
			</ends>
		</adjacency>
		<adjacency>
			<start>
				<region>
					<name>
						Hong Kong
					</name>
				</region>
			</start>
			<ends>
				<end>
					<region>
						<name>
							Astana
						</name>
					</region>
					<moves>
						<move>
							<name>
								Reinforcement
							</name>
						</move>
						<move>
							<name>
								Assault
							</name>
						</move>
					</moves>
				</end>
				<end>
					<region>
						<name>
							Novosibirsk
						</name>
					</region>
					<moves>
						<move>
							<name>
								Reinforcement
							</name>
						</move>
						<move>
							<name>
								Assault
							</name>
						</move>
					</moves>
				</end>
				<end>
					<region>
						<name>
							Delhi
						</name>
					</region>
					<moves>
						<move>
							<name>
								Reinforcement
							</name>
						</move>
						<move>
							<name>
								Assault
							</name>
						</move>
					</moves>
				</end>
				<end>
					<region>
						<name>
							Manila
						</name>
					</region>
					<moves>
						<move>
							<name>
								Reinforcement
							</name>
						</move>
						<move>
							<name>
								Assault
							</name>
						</move>
					</moves>
				</end>
				<end>
					<region>
						<name>
							Mumbai
						</name>
					</region>
					<moves>
						<move>
							<name>
								Reinforcement
							</name>
						</move>
						<move>
							<name>
								Assault
							</name>
						</move>
					</moves>
				</end>
				<end>
					<region>
						<name>
							Bangkok
						</name>
					</region>
					<moves>
						<move>
							<name>
								Reinforcement
							</name>
						</move>
						<move>
							<name>
								Assault
							</name>
						</move>
					</moves>
				</end>
			</ends>
		</adjacency>
		<adjacency>
			<start>
				<region>
					<name>
						Manila
					</name>
				</region>
			</start>
			<ends>
				<end>
					<region>
						<name>
							Novosibirsk
						</name>
					</region>
					<moves>
						<move>
							<name>
								Reinforcement
							</name>
						</move>
						<move>
							<name>
								Assault
							</name>
						</move>
					</moves>
				</end>
				<end>
					<region>
						<name>
							Beijing
						</name>
					</region>
					<moves>
						<move>
							<name>
								Reinforcement
							</name>
						</move>
						<move>
							<name>
								Assault
							</name>
						</move>
					</moves>
				</end>
				<end>
					<region>
						<name>
							Tokyo
						</name>
					</region>
					<moves>
						<move>
							<name>
								Reinforcement
							</name>
						</move>
						<move>
							<name>
								Assault
							</name>
						</move>
					</moves>
				</end>
				<end>
					<region>
						<name>
							Hong Kong
						</name>
					</region>
					<moves>
						<move>
							<name>
								Reinforcement
							</name>
						</move>
						<move>
							<name>
								Assault
							</name>
						</move>
					</moves>
				</end>
			</ends>
		</adjacency>
		<adjacency>
			<start>
				<region>
					<name>
						Mumbai
					</name>
				</region>
			</start>
			<ends>
				<end>
					<region>
						<name>
							Dubai
						</name>
					</region>
					<moves>
						<move>
							<name>
								Reinforcement
							</name>
						</move>
						<move>
							<name>
								Assault
							</name>
						</move>
					</moves>
				</end>
				<end>
					<region>
						<name>
							Delhi
						</name>
					</region>
					<moves>
						<move>
							<name>
								Reinforcement
							</name>
						</move>
						<move>
							<name>
								Assault
							</name>
						</move>
					</moves>
				</end>
				<end>
					<region>
						<name>
							Hong Kong
						</name>
					</region>
					<moves>
						<move>
							<name>
								Reinforcement
							</name>
						</move>
						<move>
							<name>
								Assault
							</name>
						</move>
					</moves>
				</end>
				<end>
					<region>
						<name>
							Bangkok
						</name>
					</region>
					<moves>
						<move>
							<name>
								Reinforcement
							</name>
						</move>
						<move>
							<name>
								Assault
							</name>
						</move>
					</moves>
				</end>
			</ends>
		</adjacency>
		<adjacency>
			<start>
				<region>
					<name>
						Bangkok
					</name>
				</region>
			</start>
			<ends>
				<end>
					<region>
						<name>
							Hong Kong
						</name>
					</region>
					<moves>
						<move>
							<name>
								Reinforcement
							</name>
						</move>
						<move>
							<name>
								Assault
							</name>
						</move>
					</moves>
				</end>
				<end>
					<region>
						<name>
							Mumbai
						</name>
					</region>
					<moves>
						<move>
							<name>
								Reinforcement
							</name>
						</move>
						<move>
							<name>
								Assault
							</name>
						</move>
					</moves>
				</end>
				<end>
					<region>
						<name>
							Jakarta
						</name>
					</region>
					<moves>
						<move>
							<name>
								Reinforcement
							</name>
						</move>
						<move>
							<name>
								Assault
							</name>
						</move>
					</moves>
				</end>
			</ends>
		</adjacency>
		<adjacency>
			<start>
				<region>
					<name>
						Jakarta
					</name>
				</region>
			</start>
			<ends>
				<end>
					<region>
						<name>
							Bangkok
						</name>
					</region>
					<moves>
						<move>
							<name>
								Reinforcement
							</name>
						</move>
						<move>
							<name>
								Assault
							</name>
						</move>
					</moves>
				</end>
				<end>
					<region>
						<name>
							Port Moresby
						</name>
					</region>
					<moves>
						<move>
							<name>
								Reinforcement
							</name>
						</move>
						<move>
							<name>
								Assault
							</name>
						</move>
					</moves>
				</end>
				<end>
					<region>
						<name>
							Perth
						</name>
					</region>
					<moves>
						<move>
							<name>
								Reinforcement
							</name>
						</move>
						<move>
							<name>
								Assault
							</name>
						</move>
					</moves>
				</end>
			</ends>
		</adjacency>
		<adjacency>
			<start>
				<region>
					<name>
						Port Moresby
					</name>
				</region>
			</start>
			<ends>
				<end>
					<region>
						<name>
							
						</name>
					</region>
					<moves>
						<move>
							<name>
								Reinforcement
							</name>
						</move>
						<move>
							<name>
								Assault
							</name>
						</move>
					</moves>
				</end>
				<end>
					<region>
						<name>
							Jakarta
						</name>
					</region>
					<moves>
						<move>
							<name>
								Reinforcement
							</name>
						</move>
						<move>
							<name>
								Assault
							</name>
						</move>
					</moves>
				</end>
				<end>
					<region>
						<name>
							Perth
						</name>
					</region>
					<moves>
						<move>
							<name>
								Reinforcement
							</name>
						</move>
						<move>
							<name>
								Assault
							</name>
						</move>
					</moves>
				</end>
				<end>
					<region>
						<name>
							Sydney
						</name>
					</region>
					<moves>
						<move>
							<name>
								Reinforcement
							</name>
						</move>
						<move>
							<name>
								Assault
							</name>
						</move>
					</moves>
				</end>
			</ends>
		</adjacency>
		<adjacency>
			<start>
				<region>
					<name>
						Perth
					</name>
				</region>
			</start>
			<ends>
				<end>
					<region>
						<name>
							Jakarta
						</name>
					</region>
					<moves>
						<move>
							<name>
								Reinforcement
							</name>
						</move>
						<move>
							<name>
								Assault
							</name>
						</move>
					</moves>
				</end>
				<end>
					<region>
						<name>
							Port Moresby
						</name>
					</region>
					<moves>
						<move>
							<name>
								Reinforcement
							</name>
						</move>
						<move>
							<name>
								Assault
							</name>
						</move>
					</moves>
				</end>
				<end>
					<region>
						<name>
							Sydney
						</name>
					</region>
					<moves>
						<move>
							<name>
								Reinforcement
							</name>
						</move>
						<move>
							<name>
								Assault
							</name>
						</move>
					</moves>
				</end>
			</ends>
		</adjacency>
		<adjacency>
			<start>
				<region>
					<name>
						Sydney
					</name>
				</region>
			</start>
			<ends>
				<end>
					<region>
						<name>
							Port Moresby
						</name>
					</region>
					<moves>
						<move>
							<name>
								Reinforcement
							</name>
						</move>
						<move>
							<name>
								Assault
							</name>
						</move>
					</moves>
				</end>
				<end>
					<region>
						<name>
							Perth
						</name>
					</region>
					<moves>
						<move>
							<name>
								Reinforcement
							</name>
						</move>
						<move>
							<name>
								Assault
							</name>
						</move>
					</moves>
				</end>
			</ends>
		</adjacency>
	</adjacencies>
	<modes>
		<mode>
			<players>
				2
			</players>
			<initial>
				40
			</initial>
		</mode>
		<mode>
			<players>
				3
			</players>
			<initial>
				35
			</initial>
		</mode>
		<mode>
			<players>
				4
			</players>
			<initial>
				30
			</initial>
		</mode>
		<mode>
			<players>
				5
			</players>
			<initial>
				25
			</initial>
		</mode>
		<mode>
			<players>
				6
			</players>
			<initial>
				20
			</initial>
		</mode>
	</modes>
	<minimal>
		3
	</minimal>
	<divisor>
		3
	</divisor>
</map>
